perip/__init__.py
perip/comm.py
perip/device_am2315.py
perip/device_srd_dc03v_sl_c.py
perip/perip.py
perip-0.1.15.dist-info/WHEEL
perip-0.1.15.dist-info/METADATA
perip-0.1.15.dist-info/RECORD
