Metadata-Version: 2.1
Name: perip
Version: 0.1.15
Summary: 
Author: David J Barnes
Author-email: david@onepointone.com
Requires-Python: >=3.7,<4.0
Classifier: Programming Language :: Python :: 3
Classifier: Programming Language :: Python :: 3.7
Classifier: Programming Language :: Python :: 3.8
Requires-Dist: aosong (>=0.0.2,<0.0.3)
Requires-Dist: redis (>=3.5.3,<4.0.0)
